comfyfusion/__init__.py
comfyfusion/server.py
comfyfusion/api/__init__.py
comfyfusion/api/comfyui_client.py
comfyfusion/fusion/__init__.py
comfyfusion/fusion/engine.py
comfyfusion/fusion/patcher.py
comfyfusion/utils/__init__.py
comfyfusion/utils/config.py
comfyfusion/utils/logger.py
comfyfusion/utils/types.py
comfyfusion/utils/workflow_discovery.py
comfyfusion_engine-1.0.1.dist-info/METADATA
comfyfusion_engine-1.0.1.dist-info/WHEEL
comfyfusion_engine-1.0.1.dist-info/entry_points.txt
comfyfusion_engine-1.0.1.dist-info/RECORD
