Metadata-Version: 2.4
Name: comfyfusion-engine
Version: 1.0.1
Summary: ComfyFusion Engine - 智能化 ComfyUI 工作流执行引擎
Project-URL: Homepage, https://github.com/comfyfusion/engine
Project-URL: Repository, https://github.com/comfyfusion/engine
Author-email: ComfyFusion Team <team@comfyfusion.com>
License: MIT
Classifier: Development Status :: 4 - Beta
Classifier: Intended Audience :: Developers
Classifier: License :: OSI Approved :: MIT License
Classifier: Programming Language :: Python :: 3
Classifier: Programming Language :: Python :: 3.9
Classifier: Programming Language :: Python :: 3.10
Classifier: Programming Language :: Python :: 3.11
Classifier: Programming Language :: Python :: 3.12
Requires-Python: >=3.9
Requires-Dist: aiofiles>=23.0.0
Requires-Dist: click>=8.0.0
Requires-Dist: deepmerge>=1.1.0
Requires-Dist: fastmcp>=2.0.0
Requires-Dist: httpx>=0.24.0
Requires-Dist: pydantic>=2.0.0
Requires-Dist: python-dotenv>=1.0.0
Requires-Dist: watchdog>=3.0.0
Requires-Dist: websockets>=12.0
Provides-Extra: dev
Requires-Dist: black>=23.0.0; extra == 'dev'
Requires-Dist: isort>=5.12.0; extra == 'dev'
Requires-Dist: mypy>=1.5.0; extra == 'dev'
Requires-Dist: pytest-asyncio>=0.21.0; extra == 'dev'
Requires-Dist: pytest>=7.0.0; extra == 'dev'
